[
  {"year": 1907, "month": 4, "day": 18, "hour": 2, "minute": 41, "sex": 1},
  {"year": 1919, "month": 11, "day": 3, "hour": 23, "minute": 12, "sex": 0},
  {"year": 1932, "month": 6, "day": 27, "hour": 14, "minute": 5, "sex": 1},
  {"year": 1946, "month": 1, "day": 9, "hour": 7, "minute": 33, "sex": 0},
  {"year": 1958, "month": 8, "day": 22, "hour": 19, "minute": 48, "sex": 1},
  {"year": 1964, "month": 12, "day": 31, "hour": 0, "minute": 2, "sex": 0},
  {"year": 1973, "month": 3, "day": 15, "hour": 11, "minute": 26, "sex": 1},
  {"year": 1981, "month": 10, "day": 6, "hour": 16, "minute": 59, "sex": 0},
  {"year": 1988, "month": 2, "day": 29, "hour": 22, "minute": 17, "sex": 1},
  {"year": 1995, "month": 5, "day": 12, "hour": 4, "minute": 44, "sex": 0},
  {"year": 2001, "month": 9, "day": 28, "hour": 13, "minute": 8, "sex": 1},
  {"year": 2009, "month": 7, "day": 1, "hour": 21, "minute": 36, "sex": 0},
  {"year": 2016, "month": 4, "day": 10, "hour": 6, "minute": 52, "sex": 1},
  {"year": 2020, "month": 11, "day": 24, "hour": 18, "minute": 20, "sex": 0},
  {"year": 2026, "month": 5, "day": 7, "hour": 12, "minute": 15, "sex": 1},
  {"year": 2034, "month": 12, "day": 2, "hour": 9, "minute": 39, "sex": 0}
]
